certainty_sims/__init__.py
certainty_sims-0.0.1.dist-info/LICENSE.txt
certainty_sims-0.0.1.dist-info/METADATA
certainty_sims-0.0.1.dist-info/WHEEL
certainty_sims-0.0.1.dist-info/top_level.txt
certainty_sims-0.0.1.dist-info/RECORD
