Metadata-Version: 2.1
Name: certainty-sims
Version: 0.0.1
Summary: Simulations to evaluate probablistic models of certainty.
Home-page: https://github.com/prijatelj/certainty-sims
Author: Derek S. Prijatelj
Author-email: dprijate@nd.edu
License: UNKNOWN
Platform: UNKNOWN
Classifier: Programming Language :: Python :: 3
Classifier: License :: OSI Approved :: MIT License
Classifier: Operating System :: OS Independent
Requires-Python: >=3.8
License-File: LICENSE.txt
